LICENSE
README.md
setup.py
moonlistclient/__init__.py
moonlistclient/client.py
moonlistclient/exceptions.py
moonlistclient/http.py
moonlistclient/webhook_manager.py
moonlistclient.egg-info/PKG-INFO
moonlistclient.egg-info/SOURCES.txt
moonlistclient.egg-info/dependency_links.txt
moonlistclient.egg-info/requires.txt
moonlistclient.egg-info/top_level.txt
moonlistclient/models/__init__.py
moonlistclient/models/api.py
moonlistclient/models/bases.py
moonlistclient/models/discord.py
moonlistclient/models/webhooks.py